{
    "patients":[
        {
            "id":"1",
            "name":"Gerald",
            "data":[
                {
                    "date": "March 1, 2022",
                    "pain":4,
                    "tiredness":3,
                    "anxiety": 7,
                    "wellbeing":10
                },
                {
                    "date": "March 2, 2022",
                    "pain":2,
                    "tiredness":2,
                    "anxiety": 5,
                    "wellbeing":10
                }
            ],
            "body_parts":[
                {
                    "head":6,
                    "left hand":1
                }
            ]
        },
        {
            "id":"2",
            "name":"Alice",
            "data":[
                {
                    "date": "March 3, 2022",
                    "pain":3,
                    "tiredness":3,
                    "anxiety": 3
                },
                {
                    "date": "March 1, 2022",
                    "pain":1,
                    "tiredness":2,
                    "anxiety": 1
                }
            ],
            "body_parts":[
                {
                    "head":3,
                    "left hand":9
                }
            ]
        }
    ]}